ColorKit/__init__.py
ColorKit/colorkit.py
ColorKitv2-0.1.0.dist-info/METADATA
ColorKitv2-0.1.0.dist-info/WHEEL
ColorKitv2-0.1.0.dist-info/top_level.txt
ColorKitv2-0.1.0.dist-info/RECORD
