Metadata-Version: 2.1
Name: ColorKitv2
Version: 0.1.0
Summary: A comprehensive Python package for advanced color manipulation and analysis
Home-page: https://github.com/bzm10/ColorKit
Author: Benjamin Mark
Author-email: bzmarkovits@yahoo.com
License: MIT
Keywords: color conversion,RGB,HEX,CMYK,HSL,LAB,LUV,XYZ,YIQ,HSV,YUV,YCbCr,LCH,LMS,color toolkit,color space,Python color,color manipulation,color analysis,color utility,python,color
Classifier: Development Status :: 5 - Production/Stable
Classifier: Intended Audience :: Developers
Classifier: Intended Audience :: Science/Research
Classifier: Programming Language :: Python :: 3
Classifier: Operating System :: Unix
Classifier: Operating System :: MacOS :: MacOS X
Classifier: Operating System :: Microsoft :: Windows
